beatmap/__init__.py
beatmap/version.py
beatmap/core/__init__.py
beatmap/core/_bet.py
beatmap/io/__init__.py
beatmap/io/_dataio.py
beatmap/io/vulcan_chex.csv
beatmap/io/vulcan_chex.txt
beatmap/utils/__init__.py
beatmap/utils/_utils.py
beatmap/vis/__init__.py
beatmap/vis/_figures.py
beatmap/vis/_settables.py
beatmap-0.3.0.dist-info/METADATA
beatmap-0.3.0.dist-info/WHEEL
beatmap-0.3.0.dist-info/licenses/LICENSE
beatmap-0.3.0.dist-info/RECORD
