Metadata-Version: 2.1
Name: beatmap
Version: 0.3.0
Summary: A tool for determining the valid P/P0 range in BET isotherms
Project-URL: Homepage, https://github.com/PMEAL/beatmap/
Project-URL: Bug Tracker, https://github.com/PMEAL/beatmap/issues
Author-email: Ellsworth Bell <ellsworth.bell@gmail.com>, Amin Sadeghi <amin.sadeghi@live.com>, David Morris <davidrpmorris@gmail.com>, Jeff Gostick <jgostick@uwaterloo.ca>
Maintainer-email: Amin Sadeghi <amin.sadeghi@live.com>, Jeff Gostick <jgostick@uwaterloo.ca>
License-Expression: MIT
License-File: LICENSE
Keywords: BET,GUI,Langmuir isotherm,Python,adsorption,material characterization,specific surface area,web app
Classifier: Development Status :: 5 - Production/Stable
Classifier: License :: OSI Approved :: MIT License
Classifier: Operating System :: OS Independent
Classifier: Programming Language :: Python :: 3
Classifier: Topic :: Scientific/Engineering
Classifier: Topic :: Scientific/Engineering :: Chemistry
Classifier: Topic :: Scientific/Engineering :: Physics
Requires-Python: >=3.9
Requires-Dist: matplotlib
Requires-Dist: numpy
Requires-Dist: pandas
Requires-Dist: prettytable
Requires-Dist: rich
Requires-Dist: scipy
Requires-Dist: seaborn
